{
  "Rooftop1": [
    {
      "icon": "../../../images/rooftop.png",
      "city": "OSLO",
      "func": "Functional Requirements",
      "type": "Type",
      "origin": "Origin",
      "sun": "Sun light",
      "main": "Maintenance needs",
      "roles": [
        {
          "title": "Rooftop Garden",
          "description": "Tekst om hvorfor Rooftop Garden er bra for alle.",
          "similarurl1": "blank",
          "similaricon1": "../../../images/rooftop.png",
          "similarurl2": "blank",
          "similaricon2": "../../../images/rooftop.png",
          "city": "OSLO",
          "func": "Functional Fea"
        }
      ],
      "functions": [
        {
          "name": "Stormwater Management",
          "icon": "../../../images/stormwater.png",
          "True/false": true
        },
        {
          "name": "Biodiverse",
          "icon": "../../../images/bee.png",
          "True/false": false
        }
      ],
      "maintenance": [
        {
          "name": "Sun: Low",
          "icon": "../../../images/sun.png"
        },
        {
          "name": "Water: Low",
          "icon": "../../../images/waterdrop.png"
        },
        {
          "name": "Soil: High",
          "icon": "../../../images/showel.png"
        }

      ],
      "description": [
        {
          "name": "Description",
          "info": "This is a description about this particular concept. This concept is a concept that looks like this and is this size and has these plants."
          
        }

      ],
      "plants": [
        {
          "plant1":{
            "name": "plante 1",
            "stormwater": true
          },
          "plant2":{
            "name": "plante 2",
            "stormwater": false
          }
          
        }
    
      ]

    }
  ],
  

  "Projects": [
    { 
      "icon": "Rooftop Garden",
      "project": [
        {
          "projectID":"",
          "project_name":"Sørengkai",
          "project_start":"21.04.2021",
          "project_end":"",
          "project_groupID":"",
          "project_img":"../../../images/rooftop.png"
        }
      ],

      "greenspace_category": [
        {
          "categoryID":"",
          "category_name":"Rooftop"
        }
      ],

      "greenspace": [
        {
          "greenspaceID": "",
          "greenspace_name": "Takterrasse",
          "price": "",
          "greenspace_project":"",
          "greenspace_category":"Rooftop"
        }
      
      ],

      "plants": [
        {
          "plantID":"",
          "pricePerM2":"",
          "from_greenery":"",
          "allergens":"",
          "friendlyness_to_bees":""
        }
      ]
  
    }
  ],
  "Members": [
    { 
      "icon": "Rooftop Garden",
      "greenspace": [
        {
          "greenspaceID": ""
        }
      
      ]
  
    }
  ]
  }
  



